.gitignore
README.rst
requirements-test.txt
requirements.txt
runtests.py
setup.py
django_qwert.egg-info/PKG-INFO
django_qwert.egg-info/SOURCES.txt
django_qwert.egg-info/dependency_links.txt
django_qwert.egg-info/not-zip-safe
django_qwert.egg-info/requires.txt
django_qwert.egg-info/top_level.txt
qwert/__init__.py
qwert/conf.py
qwert/models.py
qwert/decorators/__init__.py
qwert/decorators/with_request.py
qwert/http/__init__.py
qwert/management/__init__.py
qwert/management/create_testuser.py
qwert/management/extra_builtins.py
qwert/middleware/__init__.py
qwert/middleware/exception.py
qwert/middleware/http.py
qwert/middleware/threadlocals.py
qwert/templatetags/__init__.py
qwert/templatetags/evaluate_tag.py
qwert/templatetags/expr.py
qwert/templatetags/get_links.py
qwert/templatetags/markdown_tags.py
qwert/templatetags/truncateletters.py
qwert/templatetags/urlize_html.py
qwert/tests/__init__.py
qwert/tests/models.py
qwert/tests/test_decorators.py
qwert/tests/test_models.py
tests/database.db
tests/fixtures/initial_data.yaml
tests/src/miniblog/__init__.py
tests/src/miniblog/manage.py
tests/src/miniblog/settings.py
tests/src/miniblog/urls.py
tests/src/miniblog/blogs/__init__.py
tests/src/miniblog/blogs/forms.py
tests/src/miniblog/blogs/models.py
tests/src/miniblog/blogs/urls.py
tests/src/miniblog/blogs/views.py
tests/src/miniblog/blogs/fixtures/tests_miniblog_blogs_test.yaml
tests/src/miniblog/blogs/templates/404.html
tests/src/miniblog/blogs/templates/blogs/entry_confirm_delete.html
tests/src/miniblog/blogs/templates/blogs/entry_detail.html
tests/src/miniblog/blogs/templates/blogs/entry_form.html
tests/src/miniblog/blogs/templates/blogs/entry_list.html
tests/src/miniblog/blogs/tests/__init__.py
tests/src/miniblog/blogs/tests/test_models.py
tests/src/miniblog/blogs/tests/test_views.py
tests/static/css/style.css
tests/static/css/style.scss
tests/static/css/image/edit.png
tests/static/css/image/trash.png
tests/templates/404.html
tests/templates/base.html
tests/templates/blogs/entry_confirm_delete.html
tests/templates/blogs/entry_detail.html
tests/templates/blogs/entry_form.html
tests/templates/blogs/entry_list.html
tests/templates/registration/logged_out.html
