Metadata-Version: 1.0
Name: django-qwert
Version: 0.2.2
Summary: A trivia collection framework for Django
Home-page: https://github.com/lambdalisue/django-qwert
Author: Alisue
Author-email: lambdalisue@hashnote.net
License: MIT
Download-URL: https://github.com/lambdalisue/django-qwert/tarball/master
Keywords: django trivia snipet collection framework
Platform: UNKNOWN
Classifier: Development Status :: 3 - Alpha
Classifier: Environment :: Web Environment
Classifier: Framework :: Django
Classifier: Intended Audience :: Developers
Classifier: License :: OSI Approved :: MIT License
Classifier: Programming Language :: Python
Classifier: Topic :: Internet :: WWW/HTTP
